jarvis_os/__init__.py
jarvis_os/download_st.py
jarvis_os/main.py
jarvis_os/memory.py
jarvis_os/yapper/__init__.py
jarvis_os/yapper/constants.py
jarvis_os/yapper/core.py
jarvis_os/yapper/enhancer.py
jarvis_os/yapper/enums.py
jarvis_os/yapper/meta.py
jarvis_os/yapper/setup.py
jarvis_os/yapper/speaker.py
jarvis_os/yapper/test.py
jarvis_os/yapper/utils.py
jarvis_os-0.1.22.dist-info/licenses/LICENSE
jarvis_os-0.1.22.dist-info/METADATA
jarvis_os-0.1.22.dist-info/WHEEL
jarvis_os-0.1.22.dist-info/entry_points.txt
jarvis_os-0.1.22.dist-info/top_level.txt
jarvis_os-0.1.22.dist-info/RECORD
