Metadata-Version: 2.4
Name: jarvis-os
Version: 0.1.22
Summary: Voice assistant with AI, voice input, and system control
Author-email: Arvin Adeli <adeli.d.arvin@gmail.com>
License: Copyright 2025 Arvin Adeli
Requires-Python: >=3.8
License-File: LICENSE
Requires-Dist: vosk
Requires-Dist: pyaudio
Requires-Dist: keyboard
Requires-Dist: requests
Requires-Dist: pyttsx3
Requires-Dist: rich>=13.0
Requires-Dist: pygame
Requires-Dist: beautifulsoup4
Requires-Dist: pygetwindow
Requires-Dist: pyautogui
Requires-Dist: pywin32
Requires-Dist: psutil
Requires-Dist: google-genai>=0.3.0
Requires-Dist: protobuf>=4.23.0
Requires-Dist: google-auth>=2.20.0
Requires-Dist: grpcio>=1.56.0
Requires-Dist: fuzzywuzzy
Requires-Dist: python-Levenshtein
Requires-Dist: faiss-cpu
Requires-Dist: sentence-transformers
Requires-Dist: numpy
Requires-Dist: appdirs>=1.4.4
Dynamic: license-file
